src/__init__.py
src/_version.py
src/subgradient_descent.py
src/svm.py
src/benchmarks/__init__.py
src/benchmarks/benchmarks.py
src/benchmarks/data_loader.py
src/tests/__init__.py
src/tests/test_breast_cancer.py
src/tests/test_common.py
src/tests/test_iris.py
subgradient_svm_classifier-0.0.3.dist-info/LICENSE
subgradient_svm_classifier-0.0.3.dist-info/METADATA
subgradient_svm_classifier-0.0.3.dist-info/WHEEL
subgradient_svm_classifier-0.0.3.dist-info/top_level.txt
subgradient_svm_classifier-0.0.3.dist-info/RECORD
